[
  {
    "id": "women-multi-001",
    "name": "Women’s Essential Multivitamin",
    "price": 23.99,
    "category": "womens",
    "description": "A complete daily multivitamin formulated to support women’s energy, immunity, and hormonal balance."
  },
  {
    "id": "women-hormone-002",
    "name": "Hormone Balance Complex",
    "price": 27.99,
    "category": "womens",
    "description": "A blend of chasteberry, ashwagandha, and B‑vitamins to support mood, cycle regularity, and hormonal wellness."
  },
  {
    "id": "women-glow-003",
    "name": "Glow & Hydrate Collagen Boost",
    "price": 24.99,
    "category": "womens",
    "description": "A collagen‑supporting formula designed to promote radiant skin, hair strength, and hydration."
  },
  {
    "id": "women-probiotic-004",
    "name": "Women’s Daily Probiotic",
    "price": 19.99,
    "category": "womens",
    "description": "A targeted probiotic blend to support gut health, digestion, and feminine wellness."
  },
  {
    "id": "women-stress-005",
    "name": "Stress Relief Adaptogen Blend",
    "price": 18.99,
    "category": "womens",
    "description": "A calming adaptogenic formula with rhodiola and holy basil to support stress relief and emotional balance."
  },
  {
    "id": "women-sleep-006",
    "name": "Beauty Sleep Night Gummies",
    "price": 16.99,
    "category": "womens",
    "description": "A soothing nighttime blend with melatonin and chamomile to support deep, restorative sleep."
  },
  {
    "id": "women-energy-007",
    "name": "Clean Energy Iron + B12",
    "price": 17.99,
    "category": "womens",
    "description": "Iron and B12 support for natural energy, focus, and daily vitality."
  },
  {
    "id": "women-hair-008",
    "name": "Hair, Skin & Nails Complex",
    "price": 21.99,
    "category": "womens",
    "description": "Biotin, collagen, and silica to support strong hair, glowing skin, and healthy nails."
  }
]
